whatsapp_analyzer/__init__.py
whatsapp_analyzer/preprocessor.py
whatsapp_analyzer/read.py
whatsapp_analyzer/stats.py
whatsapp_analyzer-0.1.0.dist-info/METADATA
whatsapp_analyzer-0.1.0.dist-info/WHEEL
whatsapp_analyzer-0.1.0.dist-info/top_level.txt
whatsapp_analyzer-0.1.0.dist-info/RECORD
