Metadata-Version: 2.1
Name: whatsapp-analyzer
Version: 0.1.0
Summary: Basic Version library
Home-page: 
Author: Muhammad Masood Ur Rehman
Author-email: rehmanmasood70@gmail.com
License: MIT
Platform: UNKNOWN
Classifier: Intended Audience :: Developers
Classifier: License :: OSI Approved :: MIT License
Classifier: Programming Language :: Python
Classifier: Programming Language :: Python :: 3
Classifier: Programming Language :: Python :: 3.6
Classifier: Programming Language :: Python :: 3.7
Classifier: Programming Language :: Python :: 3.8
Classifier: Programming Language :: Python :: 3.9
Classifier: Operating System :: OS Independent
Requires-Dist: matplotlib
Requires-Dist: seaborn
Requires-Dist: urlextract
Requires-Dist: wordcloud
Requires-Dist: pandas
Requires-Dist: emoji
